mapdrums/__init__.py
mapdrums/__main__.py
mapdrums/main.py
mapdrums/data/template.drm
mapdrums-0.9.1.dist-info/METADATA
mapdrums-0.9.1.dist-info/WHEEL
mapdrums-0.9.1.dist-info/entry_points.txt
mapdrums-0.9.1.dist-info/top_level.txt
mapdrums-0.9.1.dist-info/RECORD
