Metadata-Version: 2.1
Name: mapdrums
Version: 0.9.1
Summary: Generate drum maps from input CSV file
Home-page: https://github.com/barndollarmusic/mapdrums
Author: Barndollar Music, Ltd.
Author-email: eric@barndollarmusic.com
License: UNKNOWN
Project-URL: Bug Tracker, https://github.com/barndollarmusic/mapdrums/issues
Platform: UNKNOWN
Classifier: Programming Language :: Python :: 3
Classifier: License :: OSI Approved :: Apache Software License
Classifier: Operating System :: OS Independent
Requires-Python: >=3.6
Requires-Dist: Jinja2 (>=3.1.0)
